hn_mcp_server/__init__.py
hn_mcp_server/__main__.py
hn_mcp_server/server.py
hn_mcp_server/models/__init__.py
hn_mcp_server/models/errors.py
hn_mcp_server/models/item.py
hn_mcp_server/models/search.py
hn_mcp_server/models/user.py
hn_mcp_server/services/__init__.py
hn_mcp_server/services/hn_client.py
hn_mcp_server/services/rate_limit.py
hn_mcp_server/tools/__init__.py
hn_mcp_server/tools/items.py
hn_mcp_server/tools/search.py
hn_mcp_server/tools/users.py
hn_mcp_server-1.1.0.dist-info/METADATA
hn_mcp_server-1.1.0.dist-info/WHEEL
hn_mcp_server-1.1.0.dist-info/licenses/LICENSE
hn_mcp_server-1.1.0.dist-info/RECORD
