Metadata-Version: 2.4
Name: hn-mcp-server
Version: 1.1.0
Summary: Model Context Protocol server for HackerNews API
Project-URL: Homepage, https://github.com/CyrilBaah/hn-mcp-server
Project-URL: Documentation, https://github.com/CyrilBaah/hn-mcp-server#readme
Project-URL: Repository, https://github.com/CyrilBaah/hn-mcp-server
Project-URL: Issues, https://github.com/CyrilBaah/hn-mcp-server/issues
Author: Development Team
License: MIT
License-File: LICENSE
Keywords: ai,hackernews,mcp,model-context-protocol
Classifier: Development Status :: 4 - Beta
Classifier: Intended Audience :: Developers
Classifier: License :: OSI Approved :: MIT License
Classifier: Programming Language :: Python :: 3
Classifier: Programming Language :: Python :: 3.11
Classifier: Programming Language :: Python :: 3.12
Requires-Python: >=3.11
Requires-Dist: httpx>=0.27.0
Requires-Dist: mcp>=1.0.0
Requires-Dist: pydantic-settings>=2.3.0
Requires-Dist: pydantic>=2.8.0
Provides-Extra: dev
Requires-Dist: mypy>=1.11.0; extra == 'dev'
Requires-Dist: pytest-asyncio>=0.24.0; extra == 'dev'
Requires-Dist: pytest-cov>=5.0.0; extra == 'dev'
Requires-Dist: pytest-httpx>=0.30.0; extra == 'dev'
Requires-Dist: pytest>=8.3.0; extra == 'dev'
Requires-Dist: ruff>=0.5.0; extra == 'dev'
Provides-Extra: http
Requires-Dist: sse-starlette>=2.0.0; extra == 'http'
Requires-Dist: starlette>=0.37.0; extra == 'http'
Requires-Dist: uvicorn>=0.29.0; extra == 'http'
